{
    "marketCap": 3587432775680,
    "enterpriseValue": 3641326174208,
    "trailingPE": 39.034542,
    "forwardPE": 28.568161,
    "pegRatio": null,
    "priceToBook": 63.00239,
    "beta": 1.24,
    "profitMargins": 0.23971,
    "enterpriseToRevenue": 9.312,
    "enterpriseToEbitda": 27.041,
    "52WeekChange": 0.24019432,
    "shortPercentOfFloat": 0.0093,
    "shortRatio": 3.21,
    "bookValue": 3.767,
    "priceToSalesTrailing12Months": 9.174199,
    "dividendYield": 0.0043,
    "fiveYearAvgDividendYield": 0.63,
    "payoutRatio": 0.1612,
    "trailingEps": 6.08,
    "forwardEps": 8.31,
    "revenuePerShare": 25.485,
    "grossProfits": null,
    "freeCashflow": 110846001152,
    "operatingCashflow": 118254002176,
    "revenueGrowth": 0.061,
    "grossMargins": 0.46206,
    "ebitdaMargins": 0.34437,
    "operatingMargins": 0.31171,
    "financialCurrency": "USD",
    "dividendRate": 1.0,
    "dividendDate": null,
    "exDividendDate": 1731024000
}